sentence2simvec/__init__.py
sentence2simvec/cli.py
sentence2simvec/core.py
sentence2simvec-0.0.1.dist-info/licenses/LICENSE
sentence2simvec-0.0.1.dist-info/METADATA
sentence2simvec-0.0.1.dist-info/WHEEL
sentence2simvec-0.0.1.dist-info/entry_points.txt
sentence2simvec-0.0.1.dist-info/top_level.txt
sentence2simvec-0.0.1.dist-info/RECORD
