Metadata-Version: 2.4
Name: sentence2simvec
Version: 0.0.1
Summary: Sentence similarity (0-1) with SBERT vectors - Python 3.10+
Author-email: Katsuya Hyodo <rmsdh122@yahoo.co.jp>
License-Expression: Apache-2.0
Project-URL: Homepage, https://github.com/yourname/sentence2simvec
Classifier: Programming Language :: Python :: 3.10
Classifier: Programming Language :: Python :: 3 :: Only
Classifier: Operating System :: OS Independent
Requires-Python: >=3.10
License-File: LICENSE
Requires-Dist: numpy>=1.22
Requires-Dist: sentence-transformers>=2.5.0
Dynamic: license-file
